{
  "config": {
    "configFile": "C:\\Arpita\\abPlaywrightE2Eautomation\\playwright.config.ts",
    "rootDir": "C:/Arpita/abPlaywrightE2Eautomation/tests",
    "forbidOnly": false,
    "fullyParallel": true,
    "globalSetup": null,
    "globalTeardown": null,
    "globalTimeout": 0,
    "grep": {},
    "grepInvert": null,
    "maxFailures": 0,
    "metadata": {
      "actualWorkers": 1
    },
    "preserveOutput": "always",
    "projects": [
      {
        "outputDir": "C:/Arpita/abPlaywrightE2Eautomation/test-results",
        "repeatEach": 1,
        "retries": 1,
        "metadata": {
          "actualWorkers": 1
        },
        "id": "",
        "name": "",
        "testDir": "C:/Arpita/abPlaywrightE2Eautomation/tests",
        "testIgnore": [],
        "testMatch": [
          "**/*.@(spec|test).?(c|m)[jt]s?(x)"
        ],
        "timeout": 40000
      }
    ],
    "quiet": false,
    "reporter": [
      [
        "html",
        {
          "outputFolder": "playwright-report"
        }
      ],
      [
        "json",
        {
          "outputFile": "report.json"
        }
      ]
    ],
    "reportSlowTests": {
      "max": 5,
      "threshold": 300000
    },
    "shard": null,
    "tags": [],
    "updateSnapshots": "missing",
    "updateSourceMethod": "patch",
    "version": "1.59.1",
    "workers": 4,
    "webServer": null
  },
  "suites": [
    {
      "title": "accessibility\\products-full-a11y-scan.spec.ts",
      "file": "accessibility/products-full-a11y-scan.spec.ts",
      "column": 0,
      "line": 0,
      "specs": [
        {
          "title": "Products page should have no critical accessibility violations",
          "ok": false,
          "tags": [],
          "tests": [
            {
              "timeout": 40000,
              "annotations": [],
              "expectedStatus": "passed",
              "projectId": "",
              "projectName": "",
              "results": [
                {
                  "workerIndex": 0,
                  "parallelIndex": 0,
                  "status": "failed",
                  "duration": 2529,
                  "error": {
                    "message": "Error: \u001b[2mexpect(\u001b[22m\u001b[31mreceived\u001b[39m\u001b[2m).\u001b[22mtoEqual\u001b[2m(\u001b[22m\u001b[32mexpected\u001b[39m\u001b[2m) // deep equality\u001b[22m\n\n\u001b[32m- Expected  -   1\u001b[39m\n\u001b[31m+ Received  + 162\u001b[39m\n\n\u001b[32m- Array []\u001b[39m\n\u001b[31m+ Array [\u001b[39m\n\u001b[31m+   Object {\u001b[39m\n\u001b[31m+     \"description\": \"Ensure <img> elements have alternative text or a role of none or presentation\",\u001b[39m\n\u001b[31m+     \"help\": \"Images must have alternative text\",\u001b[39m\n\u001b[31m+     \"helpUrl\": \"https://dequeuniversity.com/rules/axe/4.12/image-alt?application=playwright\",\u001b[39m\n\u001b[31m+     \"id\": \"image-alt\",\u001b[39m\n\u001b[31m+     \"impact\": \"critical\",\u001b[39m\n\u001b[31m+     \"nodes\": Array [\u001b[39m\n\u001b[31m+       Object {\u001b[39m\n\u001b[31m+         \"all\": Array [],\u001b[39m\n\u001b[31m+         \"any\": Array [\u001b[39m\n\u001b[31m+           Object {\u001b[39m\n\u001b[31m+             \"data\": null,\u001b[39m\n\u001b[31m+             \"id\": \"has-alt\",\u001b[39m\n\u001b[31m+             \"impact\": \"critical\",\u001b[39m\n\u001b[31m+             \"message\": \"Element does not have an alt attribute\",\u001b[39m\n\u001b[31m+             \"relatedNodes\": Array [],\u001b[39m\n\u001b[31m+           },\u001b[39m\n\u001b[31m+           Object {\u001b[39m\n\u001b[31m+             \"data\": null,\u001b[39m\n\u001b[31m+             \"id\": \"aria-label\",\u001b[39m\n\u001b[31m+             \"impact\": \"critical\",\u001b[39m\n\u001b[31m+             \"message\": \"aria-label attribute does not exist or is empty\",\u001b[39m\n\u001b[31m+             \"relatedNodes\": Array [],\u001b[39m\n\u001b[31m+           },\u001b[39m\n\u001b[31m+           Object {\u001b[39m\n\u001b[31m+             \"data\": null,\u001b[39m\n\u001b[31m+             \"id\": \"aria-labelledby\",\u001b[39m\n\u001b[31m+             \"impact\": \"critical\",\u001b[39m\n\u001b[31m+             \"message\": \"aria-labelledby attribute does not exist, references elements that do not exist or references elements that are empty\",\u001b[39m\n\u001b[31m+             \"relatedNodes\": Array [],\u001b[39m\n\u001b[31m+           },\u001b[39m\n\u001b[31m+           Object {\u001b[39m\n\u001b[31m+             \"data\": Object {\u001b[39m\n\u001b[31m+               \"messageKey\": \"noAttr\",\u001b[39m\n\u001b[31m+             },\u001b[39m\n\u001b[31m+             \"id\": \"non-empty-title\",\u001b[39m\n\u001b[31m+             \"impact\": \"critical\",\u001b[39m\n\u001b[31m+             \"message\": \"Element has no title attribute\",\u001b[39m\n\u001b[31m+             \"relatedNodes\": Array [],\u001b[39m\n\u001b[31m+           },\u001b[39m\n\u001b[31m+           Object {\u001b[39m\n\u001b[31m+             \"data\": null,\u001b[39m\n\u001b[31m+             \"id\": \"presentational-role\",\u001b[39m\n\u001b[31m+             \"impact\": \"critical\",\u001b[39m\n\u001b[31m+             \"message\": \"Element's default semantics were not overridden with role=\\\"none\\\" or role=\\\"presentation\\\"\",\u001b[39m\n\u001b[31m+             \"relatedNodes\": Array [],\u001b[39m\n\u001b[31m+           },\u001b[39m\n\u001b[31m+         ],\u001b[39m\n\u001b[31m+         \"failureSummary\": \"Fix any of the following:\u001b[39m\n\u001b[31m+   Element does not have an alt attribute\u001b[39m\n\u001b[31m+   aria-label attribute does not exist or is empty\u001b[39m\n\u001b[31m+   aria-labelledby attribute does not exist, references elements that do not exist or references elements that are empty\u001b[39m\n\u001b[31m+   Element has no title attribute\u001b[39m\n\u001b[31m+   Element's default semantics were not overridden with role=\\\"none\\\" or role=\\\"presentation\\\"\",\u001b[39m\n\u001b[31m+         \"html\": \"<img src=\\\"/assets/Toolsqa-DZdwt2ul.jpg\\\">\",\u001b[39m\n\u001b[31m+         \"impact\": \"critical\",\u001b[39m\n\u001b[31m+         \"none\": Array [],\u001b[39m\n\u001b[31m+         \"target\": Array [\u001b[39m\n\u001b[31m+           \"img[src$=\\\"Toolsqa-DZdwt2ul.jpg\\\"]\",\u001b[39m\n\u001b[31m+         ],\u001b[39m\n\u001b[31m+       },\u001b[39m\n\u001b[31m+     ],\u001b[39m\n\u001b[31m+     \"tags\": Array [\u001b[39m\n\u001b[31m+       \"cat.text-alternatives\",\u001b[39m\n\u001b[31m+       \"wcag2a\",\u001b[39m\n\u001b[31m+       \"wcag111\",\u001b[39m\n\u001b[31m+       \"section508\",\u001b[39m\n\u001b[31m+       \"section508.22.a\",\u001b[39m\n\u001b[31m+       \"TTv5\",\u001b[39m\n\u001b[31m+       \"TT7.a\",\u001b[39m\n\u001b[31m+       \"TT7.b\",\u001b[39m\n\u001b[31m+       \"EN-301-549\",\u001b[39m\n\u001b[31m+       \"EN-9.1.1.1\",\u001b[39m\n\u001b[31m+       \"ACT\",\u001b[39m\n\u001b[31m+       \"RGAAv4\",\u001b[39m\n\u001b[31m+       \"RGAA-1.1.1\",\u001b[39m\n\u001b[31m+     ],\u001b[39m\n\u001b[31m+   },\u001b[39m\n\u001b[31m+   Object {\u001b[39m\n\u001b[31m+     \"description\": \"Ensure links have discernible text\",\u001b[39m\n\u001b[31m+     \"help\": \"Links must have discernible text\",\u001b[39m\n\u001b[31m+     \"helpUrl\": \"https://dequeuniversity.com/rules/axe/4.12/link-name?application=playwright\",\u001b[39m\n\u001b[31m+     \"id\": \"link-name\",\u001b[39m\n\u001b[31m+     \"impact\": \"serious\",\u001b[39m\n\u001b[31m+     \"nodes\": Array [\u001b[39m\n\u001b[31m+       Object {\u001b[39m\n\u001b[31m+         \"all\": Array [],\u001b[39m\n\u001b[31m+         \"any\": Array [\u001b[39m\n\u001b[31m+           Object {\u001b[39m\n\u001b[31m+             \"data\": null,\u001b[39m\n\u001b[31m+             \"id\": \"has-visible-text\",\u001b[39m\n\u001b[31m+             \"impact\": \"serious\",\u001b[39m\n\u001b[31m+             \"message\": \"Element does not have text that is visible to screen readers\",\u001b[39m\n\u001b[31m+             \"relatedNodes\": Array [],\u001b[39m\n\u001b[31m+           },\u001b[39m\n\u001b[31m+           Object {\u001b[39m\n\u001b[31m+             \"data\": null,\u001b[39m\n\u001b[31m+             \"id\": \"aria-label\",\u001b[39m\n\u001b[31m+             \"impact\": \"serious\",\u001b[39m\n\u001b[31m+             \"message\": \"aria-label attribute does not exist or is empty\",\u001b[39m\n\u001b[31m+             \"relatedNodes\": Array [],\u001b[39m\n\u001b[31m+           },\u001b[39m\n\u001b[31m+           Object {\u001b[39m\n\u001b[31m+             \"data\": null,\u001b[39m\n\u001b[31m+             \"id\": \"aria-labelledby\",\u001b[39m\n\u001b[31m+             \"impact\": \"serious\",\u001b[39m\n\u001b[31m+             \"message\": \"aria-labelledby attribute does not exist, references elements that do not exist or references elements that are empty\",\u001b[39m\n\u001b[31m+             \"relatedNodes\": Array [],\u001b[39m\n\u001b[31m+           },\u001b[39m\n\u001b[31m+           Object {\u001b[39m\n\u001b[31m+             \"data\": Object {\u001b[39m\n\u001b[31m+               \"messageKey\": \"noAttr\",\u001b[39m\n\u001b[31m+             },\u001b[39m\n\u001b[31m+             \"id\": \"non-empty-title\",\u001b[39m\n\u001b[31m+             \"impact\": \"serious\",\u001b[39m\n\u001b[31m+             \"message\": \"Element has no title attribute\",\u001b[39m\n\u001b[31m+             \"relatedNodes\": Array [],\u001b[39m\n\u001b[31m+           },\u001b[39m\n\u001b[31m+         ],\u001b[39m\n\u001b[31m+         \"failureSummary\": \"Fix all of the following:\u001b[39m\n\u001b[31m+   Element is in tab order and does not have accessible text\u001b[39m\n\u001b[31m+\u001b[39m\n\u001b[31m+ Fix any of the following:\u001b[39m\n\u001b[31m+   Element does not have text that is visible to screen readers\u001b[39m\n\u001b[31m+   aria-label attribute does not exist or is empty\u001b[39m\n\u001b[31m+   aria-labelledby attribute does not exist, references elements that do not exist or references elements that are empty\u001b[39m\n\u001b[31m+   Element has no title attribute\",\u001b[39m\n\u001b[31m+         \"html\": \"<a href=\\\"https://demoqa.com\\\"><img src=\\\"/assets/Toolsqa-DZdwt2ul.jpg\\\"></a>\",\u001b[39m\n\u001b[31m+         \"impact\": \"serious\",\u001b[39m\n\u001b[31m+         \"none\": Array [\u001b[39m\n\u001b[31m+           Object {\u001b[39m\n\u001b[31m+             \"data\": null,\u001b[39m\n\u001b[31m+             \"id\": \"focusable-no-name\",\u001b[39m\n\u001b[31m+             \"impact\": \"serious\",\u001b[39m\n\u001b[31m+             \"message\": \"Element is in tab order and does not have accessible text\",\u001b[39m\n\u001b[31m+             \"relatedNodes\": Array [],\u001b[39m\n\u001b[31m+           },\u001b[39m\n\u001b[31m+         ],\u001b[39m\n\u001b[31m+         \"target\": Array [\u001b[39m\n\u001b[31m+           \"a[href$=\\\"demoqa.com\\\"]\",\u001b[39m\n\u001b[31m+         ],\u001b[39m\n\u001b[31m+       },\u001b[39m\n\u001b[31m+     ],\u001b[39m\n\u001b[31m+     \"tags\": Array [\u001b[39m\n\u001b[31m+       \"cat.name-role-value\",\u001b[39m\n\u001b[31m+       \"wcag2a\",\u001b[39m\n\u001b[31m+       \"wcag244\",\u001b[39m\n\u001b[31m+       \"wcag412\",\u001b[39m\n\u001b[31m+       \"section508\",\u001b[39m\n\u001b[31m+       \"section508.22.a\",\u001b[39m\n\u001b[31m+       \"TTv5\",\u001b[39m\n\u001b[31m+       \"TT6.a\",\u001b[39m\n\u001b[31m+       \"EN-301-549\",\u001b[39m\n\u001b[31m+       \"EN-9.2.4.4\",\u001b[39m\n\u001b[31m+       \"EN-9.4.1.2\",\u001b[39m\n\u001b[31m+       \"ACT\",\u001b[39m\n\u001b[31m+       \"RGAAv4\",\u001b[39m\n\u001b[31m+       \"RGAA-6.2.1\",\u001b[39m\n\u001b[31m+     ],\u001b[39m\n\u001b[31m+   },\u001b[39m\n\u001b[31m+ ]\u001b[39m",
                    "stack": "Error: \u001b[2mexpect(\u001b[22m\u001b[31mreceived\u001b[39m\u001b[2m).\u001b[22mtoEqual\u001b[2m(\u001b[22m\u001b[32mexpected\u001b[39m\u001b[2m) // deep equality\u001b[22m\n\n\u001b[32m- Expected  -   1\u001b[39m\n\u001b[31m+ Received  + 162\u001b[39m\n\n\u001b[32m- Array []\u001b[39m\n\u001b[31m+ Array [\u001b[39m\n\u001b[31m+   Object {\u001b[39m\n\u001b[31m+     \"description\": \"Ensure <img> elements have alternative text or a role of none or presentation\",\u001b[39m\n\u001b[31m+     \"help\": \"Images must have alternative text\",\u001b[39m\n\u001b[31m+     \"helpUrl\": \"https://dequeuniversity.com/rules/axe/4.12/image-alt?application=playwright\",\u001b[39m\n\u001b[31m+     \"id\": \"image-alt\",\u001b[39m\n\u001b[31m+     \"impact\": \"critical\",\u001b[39m\n\u001b[31m+     \"nodes\": Array [\u001b[39m\n\u001b[31m+       Object {\u001b[39m\n\u001b[31m+         \"all\": Array [],\u001b[39m\n\u001b[31m+         \"any\": Array [\u001b[39m\n\u001b[31m+           Object {\u001b[39m\n\u001b[31m+             \"data\": null,\u001b[39m\n\u001b[31m+             \"id\": \"has-alt\",\u001b[39m\n\u001b[31m+             \"impact\": \"critical\",\u001b[39m\n\u001b[31m+             \"message\": \"Element does not have an alt attribute\",\u001b[39m\n\u001b[31m+             \"relatedNodes\": Array [],\u001b[39m\n\u001b[31m+           },\u001b[39m\n\u001b[31m+           Object {\u001b[39m\n\u001b[31m+             \"data\": null,\u001b[39m\n\u001b[31m+             \"id\": \"aria-label\",\u001b[39m\n\u001b[31m+             \"impact\": \"critical\",\u001b[39m\n\u001b[31m+             \"message\": \"aria-label attribute does not exist or is empty\",\u001b[39m\n\u001b[31m+             \"relatedNodes\": Array [],\u001b[39m\n\u001b[31m+           },\u001b[39m\n\u001b[31m+           Object {\u001b[39m\n\u001b[31m+             \"data\": null,\u001b[39m\n\u001b[31m+             \"id\": \"aria-labelledby\",\u001b[39m\n\u001b[31m+             \"impact\": \"critical\",\u001b[39m\n\u001b[31m+             \"message\": \"aria-labelledby attribute does not exist, references elements that do not exist or references elements that are empty\",\u001b[39m\n\u001b[31m+             \"relatedNodes\": Array [],\u001b[39m\n\u001b[31m+           },\u001b[39m\n\u001b[31m+           Object {\u001b[39m\n\u001b[31m+             \"data\": Object {\u001b[39m\n\u001b[31m+               \"messageKey\": \"noAttr\",\u001b[39m\n\u001b[31m+             },\u001b[39m\n\u001b[31m+             \"id\": \"non-empty-title\",\u001b[39m\n\u001b[31m+             \"impact\": \"critical\",\u001b[39m\n\u001b[31m+             \"message\": \"Element has no title attribute\",\u001b[39m\n\u001b[31m+             \"relatedNodes\": Array [],\u001b[39m\n\u001b[31m+           },\u001b[39m\n\u001b[31m+           Object {\u001b[39m\n\u001b[31m+             \"data\": null,\u001b[39m\n\u001b[31m+             \"id\": \"presentational-role\",\u001b[39m\n\u001b[31m+             \"impact\": \"critical\",\u001b[39m\n\u001b[31m+             \"message\": \"Element's default semantics were not overridden with role=\\\"none\\\" or role=\\\"presentation\\\"\",\u001b[39m\n\u001b[31m+             \"relatedNodes\": Array [],\u001b[39m\n\u001b[31m+           },\u001b[39m\n\u001b[31m+         ],\u001b[39m\n\u001b[31m+         \"failureSummary\": \"Fix any of the following:\u001b[39m\n\u001b[31m+   Element does not have an alt attribute\u001b[39m\n\u001b[31m+   aria-label attribute does not exist or is empty\u001b[39m\n\u001b[31m+   aria-labelledby attribute does not exist, references elements that do not exist or references elements that are empty\u001b[39m\n\u001b[31m+   Element has no title attribute\u001b[39m\n\u001b[31m+   Element's default semantics were not overridden with role=\\\"none\\\" or role=\\\"presentation\\\"\",\u001b[39m\n\u001b[31m+         \"html\": \"<img src=\\\"/assets/Toolsqa-DZdwt2ul.jpg\\\">\",\u001b[39m\n\u001b[31m+         \"impact\": \"critical\",\u001b[39m\n\u001b[31m+         \"none\": Array [],\u001b[39m\n\u001b[31m+         \"target\": Array [\u001b[39m\n\u001b[31m+           \"img[src$=\\\"Toolsqa-DZdwt2ul.jpg\\\"]\",\u001b[39m\n\u001b[31m+         ],\u001b[39m\n\u001b[31m+       },\u001b[39m\n\u001b[31m+     ],\u001b[39m\n\u001b[31m+     \"tags\": Array [\u001b[39m\n\u001b[31m+       \"cat.text-alternatives\",\u001b[39m\n\u001b[31m+       \"wcag2a\",\u001b[39m\n\u001b[31m+       \"wcag111\",\u001b[39m\n\u001b[31m+       \"section508\",\u001b[39m\n\u001b[31m+       \"section508.22.a\",\u001b[39m\n\u001b[31m+       \"TTv5\",\u001b[39m\n\u001b[31m+       \"TT7.a\",\u001b[39m\n\u001b[31m+       \"TT7.b\",\u001b[39m\n\u001b[31m+       \"EN-301-549\",\u001b[39m\n\u001b[31m+       \"EN-9.1.1.1\",\u001b[39m\n\u001b[31m+       \"ACT\",\u001b[39m\n\u001b[31m+       \"RGAAv4\",\u001b[39m\n\u001b[31m+       \"RGAA-1.1.1\",\u001b[39m\n\u001b[31m+     ],\u001b[39m\n\u001b[31m+   },\u001b[39m\n\u001b[31m+   Object {\u001b[39m\n\u001b[31m+     \"description\": \"Ensure links have discernible text\",\u001b[39m\n\u001b[31m+     \"help\": \"Links must have discernible text\",\u001b[39m\n\u001b[31m+     \"helpUrl\": \"https://dequeuniversity.com/rules/axe/4.12/link-name?application=playwright\",\u001b[39m\n\u001b[31m+     \"id\": \"link-name\",\u001b[39m\n\u001b[31m+     \"impact\": \"serious\",\u001b[39m\n\u001b[31m+     \"nodes\": Array [\u001b[39m\n\u001b[31m+       Object {\u001b[39m\n\u001b[31m+         \"all\": Array [],\u001b[39m\n\u001b[31m+         \"any\": Array [\u001b[39m\n\u001b[31m+           Object {\u001b[39m\n\u001b[31m+             \"data\": null,\u001b[39m\n\u001b[31m+             \"id\": \"has-visible-text\",\u001b[39m\n\u001b[31m+             \"impact\": \"serious\",\u001b[39m\n\u001b[31m+             \"message\": \"Element does not have text that is visible to screen readers\",\u001b[39m\n\u001b[31m+             \"relatedNodes\": Array [],\u001b[39m\n\u001b[31m+           },\u001b[39m\n\u001b[31m+           Object {\u001b[39m\n\u001b[31m+             \"data\": null,\u001b[39m\n\u001b[31m+             \"id\": \"aria-label\",\u001b[39m\n\u001b[31m+             \"impact\": \"serious\",\u001b[39m\n\u001b[31m+             \"message\": \"aria-label attribute does not exist or is empty\",\u001b[39m\n\u001b[31m+             \"relatedNodes\": Array [],\u001b[39m\n\u001b[31m+           },\u001b[39m\n\u001b[31m+           Object {\u001b[39m\n\u001b[31m+             \"data\": null,\u001b[39m\n\u001b[31m+             \"id\": \"aria-labelledby\",\u001b[39m\n\u001b[31m+             \"impact\": \"serious\",\u001b[39m\n\u001b[31m+             \"message\": \"aria-labelledby attribute does not exist, references elements that do not exist or references elements that are empty\",\u001b[39m\n\u001b[31m+             \"relatedNodes\": Array [],\u001b[39m\n\u001b[31m+           },\u001b[39m\n\u001b[31m+           Object {\u001b[39m\n\u001b[31m+             \"data\": Object {\u001b[39m\n\u001b[31m+               \"messageKey\": \"noAttr\",\u001b[39m\n\u001b[31m+             },\u001b[39m\n\u001b[31m+             \"id\": \"non-empty-title\",\u001b[39m\n\u001b[31m+             \"impact\": \"serious\",\u001b[39m\n\u001b[31m+             \"message\": \"Element has no title attribute\",\u001b[39m\n\u001b[31m+             \"relatedNodes\": Array [],\u001b[39m\n\u001b[31m+           },\u001b[39m\n\u001b[31m+         ],\u001b[39m\n\u001b[31m+         \"failureSummary\": \"Fix all of the following:\u001b[39m\n\u001b[31m+   Element is in tab order and does not have accessible text\u001b[39m\n\u001b[31m+\u001b[39m\n\u001b[31m+ Fix any of the following:\u001b[39m\n\u001b[31m+   Element does not have text that is visible to screen readers\u001b[39m\n\u001b[31m+   aria-label attribute does not exist or is empty\u001b[39m\n\u001b[31m+   aria-labelledby attribute does not exist, references elements that do not exist or references elements that are empty\u001b[39m\n\u001b[31m+   Element has no title attribute\",\u001b[39m\n\u001b[31m+         \"html\": \"<a href=\\\"https://demoqa.com\\\"><img src=\\\"/assets/Toolsqa-DZdwt2ul.jpg\\\"></a>\",\u001b[39m\n\u001b[31m+         \"impact\": \"serious\",\u001b[39m\n\u001b[31m+         \"none\": Array [\u001b[39m\n\u001b[31m+           Object {\u001b[39m\n\u001b[31m+             \"data\": null,\u001b[39m\n\u001b[31m+             \"id\": \"focusable-no-name\",\u001b[39m\n\u001b[31m+             \"impact\": \"serious\",\u001b[39m\n\u001b[31m+             \"message\": \"Element is in tab order and does not have accessible text\",\u001b[39m\n\u001b[31m+             \"relatedNodes\": Array [],\u001b[39m\n\u001b[31m+           },\u001b[39m\n\u001b[31m+         ],\u001b[39m\n\u001b[31m+         \"target\": Array [\u001b[39m\n\u001b[31m+           \"a[href$=\\\"demoqa.com\\\"]\",\u001b[39m\n\u001b[31m+         ],\u001b[39m\n\u001b[31m+       },\u001b[39m\n\u001b[31m+     ],\u001b[39m\n\u001b[31m+     \"tags\": Array [\u001b[39m\n\u001b[31m+       \"cat.name-role-value\",\u001b[39m\n\u001b[31m+       \"wcag2a\",\u001b[39m\n\u001b[31m+       \"wcag244\",\u001b[39m\n\u001b[31m+       \"wcag412\",\u001b[39m\n\u001b[31m+       \"section508\",\u001b[39m\n\u001b[31m+       \"section508.22.a\",\u001b[39m\n\u001b[31m+       \"TTv5\",\u001b[39m\n\u001b[31m+       \"TT6.a\",\u001b[39m\n\u001b[31m+       \"EN-301-549\",\u001b[39m\n\u001b[31m+       \"EN-9.2.4.4\",\u001b[39m\n\u001b[31m+       \"EN-9.4.1.2\",\u001b[39m\n\u001b[31m+       \"ACT\",\u001b[39m\n\u001b[31m+       \"RGAAv4\",\u001b[39m\n\u001b[31m+       \"RGAA-6.2.1\",\u001b[39m\n\u001b[31m+     ],\u001b[39m\n\u001b[31m+   },\u001b[39m\n\u001b[31m+ ]\u001b[39m\n    at C:\\Arpita\\abPlaywrightE2Eautomation\\tests\\accessibility\\products-full-a11y-scan.spec.ts:30:5",
                    "location": {
                      "file": "C:\\Arpita\\abPlaywrightE2Eautomation\\tests\\accessibility\\products-full-a11y-scan.spec.ts",
                      "column": 5,
                      "line": 30
                    },
                    "snippet": "\u001b[0m \u001b[90m 28 |\u001b[39m   expect(\n \u001b[90m 29 |\u001b[39m     accessibilityScanResults\u001b[33m.\u001b[39mviolations\n\u001b[31m\u001b[1m>\u001b[22m\u001b[39m\u001b[90m 30 |\u001b[39m   )\u001b[33m.\u001b[39mtoEqual([])\u001b[33m;\u001b[39m\n \u001b[90m    |\u001b[39m     \u001b[31m\u001b[1m^\u001b[22m\u001b[39m\n \u001b[90m 31 |\u001b[39m })\u001b[33m;\u001b[39m\u001b[0m"
                  },
                  "errors": [
                    {
                      "location": {
                        "file": "C:\\Arpita\\abPlaywrightE2Eautomation\\tests\\accessibility\\products-full-a11y-scan.spec.ts",
                        "column": 5,
                        "line": 30
                      },
                      "message": "Error: \u001b[2mexpect(\u001b[22m\u001b[31mreceived\u001b[39m\u001b[2m).\u001b[22mtoEqual\u001b[2m(\u001b[22m\u001b[32mexpected\u001b[39m\u001b[2m) // deep equality\u001b[22m\n\n\u001b[32m- Expected  -   1\u001b[39m\n\u001b[31m+ Received  + 162\u001b[39m\n\n\u001b[32m- Array []\u001b[39m\n\u001b[31m+ Array [\u001b[39m\n\u001b[31m+   Object {\u001b[39m\n\u001b[31m+     \"description\": \"Ensure <img> elements have alternative text or a role of none or presentation\",\u001b[39m\n\u001b[31m+     \"help\": \"Images must have alternative text\",\u001b[39m\n\u001b[31m+     \"helpUrl\": \"https://dequeuniversity.com/rules/axe/4.12/image-alt?application=playwright\",\u001b[39m\n\u001b[31m+     \"id\": \"image-alt\",\u001b[39m\n\u001b[31m+     \"impact\": \"critical\",\u001b[39m\n\u001b[31m+     \"nodes\": Array [\u001b[39m\n\u001b[31m+       Object {\u001b[39m\n\u001b[31m+         \"all\": Array [],\u001b[39m\n\u001b[31m+         \"any\": Array [\u001b[39m\n\u001b[31m+           Object {\u001b[39m\n\u001b[31m+             \"data\": null,\u001b[39m\n\u001b[31m+             \"id\": \"has-alt\",\u001b[39m\n\u001b[31m+             \"impact\": \"critical\",\u001b[39m\n\u001b[31m+             \"message\": \"Element does not have an alt attribute\",\u001b[39m\n\u001b[31m+             \"relatedNodes\": Array [],\u001b[39m\n\u001b[31m+           },\u001b[39m\n\u001b[31m+           Object {\u001b[39m\n\u001b[31m+             \"data\": null,\u001b[39m\n\u001b[31m+             \"id\": \"aria-label\",\u001b[39m\n\u001b[31m+             \"impact\": \"critical\",\u001b[39m\n\u001b[31m+             \"message\": \"aria-label attribute does not exist or is empty\",\u001b[39m\n\u001b[31m+             \"relatedNodes\": Array [],\u001b[39m\n\u001b[31m+           },\u001b[39m\n\u001b[31m+           Object {\u001b[39m\n\u001b[31m+             \"data\": null,\u001b[39m\n\u001b[31m+             \"id\": \"aria-labelledby\",\u001b[39m\n\u001b[31m+             \"impact\": \"critical\",\u001b[39m\n\u001b[31m+             \"message\": \"aria-labelledby attribute does not exist, references elements that do not exist or references elements that are empty\",\u001b[39m\n\u001b[31m+             \"relatedNodes\": Array [],\u001b[39m\n\u001b[31m+           },\u001b[39m\n\u001b[31m+           Object {\u001b[39m\n\u001b[31m+             \"data\": Object {\u001b[39m\n\u001b[31m+               \"messageKey\": \"noAttr\",\u001b[39m\n\u001b[31m+             },\u001b[39m\n\u001b[31m+             \"id\": \"non-empty-title\",\u001b[39m\n\u001b[31m+             \"impact\": \"critical\",\u001b[39m\n\u001b[31m+             \"message\": \"Element has no title attribute\",\u001b[39m\n\u001b[31m+             \"relatedNodes\": Array [],\u001b[39m\n\u001b[31m+           },\u001b[39m\n\u001b[31m+           Object {\u001b[39m\n\u001b[31m+             \"data\": null,\u001b[39m\n\u001b[31m+             \"id\": \"presentational-role\",\u001b[39m\n\u001b[31m+             \"impact\": \"critical\",\u001b[39m\n\u001b[31m+             \"message\": \"Element's default semantics were not overridden with role=\\\"none\\\" or role=\\\"presentation\\\"\",\u001b[39m\n\u001b[31m+             \"relatedNodes\": Array [],\u001b[39m\n\u001b[31m+           },\u001b[39m\n\u001b[31m+         ],\u001b[39m\n\u001b[31m+         \"failureSummary\": \"Fix any of the following:\u001b[39m\n\u001b[31m+   Element does not have an alt attribute\u001b[39m\n\u001b[31m+   aria-label attribute does not exist or is empty\u001b[39m\n\u001b[31m+   aria-labelledby attribute does not exist, references elements that do not exist or references elements that are empty\u001b[39m\n\u001b[31m+   Element has no title attribute\u001b[39m\n\u001b[31m+   Element's default semantics were not overridden with role=\\\"none\\\" or role=\\\"presentation\\\"\",\u001b[39m\n\u001b[31m+         \"html\": \"<img src=\\\"/assets/Toolsqa-DZdwt2ul.jpg\\\">\",\u001b[39m\n\u001b[31m+         \"impact\": \"critical\",\u001b[39m\n\u001b[31m+         \"none\": Array [],\u001b[39m\n\u001b[31m+         \"target\": Array [\u001b[39m\n\u001b[31m+           \"img[src$=\\\"Toolsqa-DZdwt2ul.jpg\\\"]\",\u001b[39m\n\u001b[31m+         ],\u001b[39m\n\u001b[31m+       },\u001b[39m\n\u001b[31m+     ],\u001b[39m\n\u001b[31m+     \"tags\": Array [\u001b[39m\n\u001b[31m+       \"cat.text-alternatives\",\u001b[39m\n\u001b[31m+       \"wcag2a\",\u001b[39m\n\u001b[31m+       \"wcag111\",\u001b[39m\n\u001b[31m+       \"section508\",\u001b[39m\n\u001b[31m+       \"section508.22.a\",\u001b[39m\n\u001b[31m+       \"TTv5\",\u001b[39m\n\u001b[31m+       \"TT7.a\",\u001b[39m\n\u001b[31m+       \"TT7.b\",\u001b[39m\n\u001b[31m+       \"EN-301-549\",\u001b[39m\n\u001b[31m+       \"EN-9.1.1.1\",\u001b[39m\n\u001b[31m+       \"ACT\",\u001b[39m\n\u001b[31m+       \"RGAAv4\",\u001b[39m\n\u001b[31m+       \"RGAA-1.1.1\",\u001b[39m\n\u001b[31m+     ],\u001b[39m\n\u001b[31m+   },\u001b[39m\n\u001b[31m+   Object {\u001b[39m\n\u001b[31m+     \"description\": \"Ensure links have discernible text\",\u001b[39m\n\u001b[31m+     \"help\": \"Links must have discernible text\",\u001b[39m\n\u001b[31m+     \"helpUrl\": \"https://dequeuniversity.com/rules/axe/4.12/link-name?application=playwright\",\u001b[39m\n\u001b[31m+     \"id\": \"link-name\",\u001b[39m\n\u001b[31m+     \"impact\": \"serious\",\u001b[39m\n\u001b[31m+     \"nodes\": Array [\u001b[39m\n\u001b[31m+       Object {\u001b[39m\n\u001b[31m+         \"all\": Array [],\u001b[39m\n\u001b[31m+         \"any\": Array [\u001b[39m\n\u001b[31m+           Object {\u001b[39m\n\u001b[31m+             \"data\": null,\u001b[39m\n\u001b[31m+             \"id\": \"has-visible-text\",\u001b[39m\n\u001b[31m+             \"impact\": \"serious\",\u001b[39m\n\u001b[31m+             \"message\": \"Element does not have text that is visible to screen readers\",\u001b[39m\n\u001b[31m+             \"relatedNodes\": Array [],\u001b[39m\n\u001b[31m+           },\u001b[39m\n\u001b[31m+           Object {\u001b[39m\n\u001b[31m+             \"data\": null,\u001b[39m\n\u001b[31m+             \"id\": \"aria-label\",\u001b[39m\n\u001b[31m+             \"impact\": \"serious\",\u001b[39m\n\u001b[31m+             \"message\": \"aria-label attribute does not exist or is empty\",\u001b[39m\n\u001b[31m+             \"relatedNodes\": Array [],\u001b[39m\n\u001b[31m+           },\u001b[39m\n\u001b[31m+           Object {\u001b[39m\n\u001b[31m+             \"data\": null,\u001b[39m\n\u001b[31m+             \"id\": \"aria-labelledby\",\u001b[39m\n\u001b[31m+             \"impact\": \"serious\",\u001b[39m\n\u001b[31m+             \"message\": \"aria-labelledby attribute does not exist, references elements that do not exist or references elements that are empty\",\u001b[39m\n\u001b[31m+             \"relatedNodes\": Array [],\u001b[39m\n\u001b[31m+           },\u001b[39m\n\u001b[31m+           Object {\u001b[39m\n\u001b[31m+             \"data\": Object {\u001b[39m\n\u001b[31m+               \"messageKey\": \"noAttr\",\u001b[39m\n\u001b[31m+             },\u001b[39m\n\u001b[31m+             \"id\": \"non-empty-title\",\u001b[39m\n\u001b[31m+             \"impact\": \"serious\",\u001b[39m\n\u001b[31m+             \"message\": \"Element has no title attribute\",\u001b[39m\n\u001b[31m+             \"relatedNodes\": Array [],\u001b[39m\n\u001b[31m+           },\u001b[39m\n\u001b[31m+         ],\u001b[39m\n\u001b[31m+         \"failureSummary\": \"Fix all of the following:\u001b[39m\n\u001b[31m+   Element is in tab order and does not have accessible text\u001b[39m\n\u001b[31m+\u001b[39m\n\u001b[31m+ Fix any of the following:\u001b[39m\n\u001b[31m+   Element does not have text that is visible to screen readers\u001b[39m\n\u001b[31m+   aria-label attribute does not exist or is empty\u001b[39m\n\u001b[31m+   aria-labelledby attribute does not exist, references elements that do not exist or references elements that are empty\u001b[39m\n\u001b[31m+   Element has no title attribute\",\u001b[39m\n\u001b[31m+         \"html\": \"<a href=\\\"https://demoqa.com\\\"><img src=\\\"/assets/Toolsqa-DZdwt2ul.jpg\\\"></a>\",\u001b[39m\n\u001b[31m+         \"impact\": \"serious\",\u001b[39m\n\u001b[31m+         \"none\": Array [\u001b[39m\n\u001b[31m+           Object {\u001b[39m\n\u001b[31m+             \"data\": null,\u001b[39m\n\u001b[31m+             \"id\": \"focusable-no-name\",\u001b[39m\n\u001b[31m+             \"impact\": \"serious\",\u001b[39m\n\u001b[31m+             \"message\": \"Element is in tab order and does not have accessible text\",\u001b[39m\n\u001b[31m+             \"relatedNodes\": Array [],\u001b[39m\n\u001b[31m+           },\u001b[39m\n\u001b[31m+         ],\u001b[39m\n\u001b[31m+         \"target\": Array [\u001b[39m\n\u001b[31m+           \"a[href$=\\\"demoqa.com\\\"]\",\u001b[39m\n\u001b[31m+         ],\u001b[39m\n\u001b[31m+       },\u001b[39m\n\u001b[31m+     ],\u001b[39m\n\u001b[31m+     \"tags\": Array [\u001b[39m\n\u001b[31m+       \"cat.name-role-value\",\u001b[39m\n\u001b[31m+       \"wcag2a\",\u001b[39m\n\u001b[31m+       \"wcag244\",\u001b[39m\n\u001b[31m+       \"wcag412\",\u001b[39m\n\u001b[31m+       \"section508\",\u001b[39m\n\u001b[31m+       \"section508.22.a\",\u001b[39m\n\u001b[31m+       \"TTv5\",\u001b[39m\n\u001b[31m+       \"TT6.a\",\u001b[39m\n\u001b[31m+       \"EN-301-549\",\u001b[39m\n\u001b[31m+       \"EN-9.2.4.4\",\u001b[39m\n\u001b[31m+       \"EN-9.4.1.2\",\u001b[39m\n\u001b[31m+       \"ACT\",\u001b[39m\n\u001b[31m+       \"RGAAv4\",\u001b[39m\n\u001b[31m+       \"RGAA-6.2.1\",\u001b[39m\n\u001b[31m+     ],\u001b[39m\n\u001b[31m+   },\u001b[39m\n\u001b[31m+ ]\u001b[39m\n\n\u001b[0m \u001b[90m 28 |\u001b[39m   expect(\n \u001b[90m 29 |\u001b[39m     accessibilityScanResults\u001b[33m.\u001b[39mviolations\n\u001b[31m\u001b[1m>\u001b[22m\u001b[39m\u001b[90m 30 |\u001b[39m   )\u001b[33m.\u001b[39mtoEqual([])\u001b[33m;\u001b[39m\n \u001b[90m    |\u001b[39m     \u001b[31m\u001b[1m^\u001b[22m\u001b[39m\n \u001b[90m 31 |\u001b[39m })\u001b[33m;\u001b[39m\u001b[0m\n\u001b[2m    at C:\\Arpita\\abPlaywrightE2Eautomation\\tests\\accessibility\\products-full-a11y-scan.spec.ts:30:5\u001b[22m"
                    }
                  ],
                  "stdout": [
                    {
                      "text": "[\n  {\n    \"id\": \"image-alt\",\n    \"impact\": \"critical\",\n    \"tags\": [\n      \"cat.text-alternatives\",\n      \"wcag2a\",\n      \"wcag111\",\n      \"section508\",\n      \"section508.22.a\",\n      \"TTv5\",\n      \"TT7.a\",\n      \"TT7.b\",\n      \"EN-301-549\",\n      \"EN-9.1.1.1\",\n      \"ACT\",\n      \"RGAAv4\",\n      \"RGAA-1.1.1\"\n    ],\n    \"description\": \"Ensure <img> elements have alternative text or a role of none or presentation\",\n    \"help\": \"Images must have alternative text\",\n    \"helpUrl\": \"https://dequeuniversity.com/rules/axe/4.12/image-alt?application=playwright\",\n    \"nodes\": [\n      {\n        \"any\": [\n          {\n            \"id\": \"has-alt\",\n            \"data\": null,\n            \"relatedNodes\": [],\n            \"impact\": \"critical\",\n            \"message\": \"Element does not have an alt attribute\"\n          },\n          {\n            \"id\": \"aria-label\",\n            \"data\": null,\n            \"relatedNodes\": [],\n            \"impact\": \"critical\",\n            \"message\": \"aria-label attribute does not exist or is empty\"\n          },\n          {\n            \"id\": \"aria-labelledby\",\n            \"data\": null,\n            \"relatedNodes\": [],\n            \"impact\": \"critical\",\n            \"message\": \"aria-labelledby attribute does not exist, references elements that do not exist or references elements that are empty\"\n          },\n          {\n            \"id\": \"non-empty-title\",\n            \"data\": {\n              \"messageKey\": \"noAttr\"\n            },\n            \"relatedNodes\": [],\n            \"impact\": \"critical\",\n            \"message\": \"Element has no title attribute\"\n          },\n          {\n            \"id\": \"presentational-role\",\n            \"data\": null,\n            \"relatedNodes\": [],\n            \"impact\": \"critical\",\n            \"message\": \"Element's default semantics were not overridden with role=\\\"none\\\" or role=\\\"presentation\\\"\"\n          }\n        ],\n        \"all\": [],\n        \"none\": [],\n        \"impact\": \"critical\",\n        \"html\": \"<img src=\\\"/assets/Toolsqa-DZdwt2ul.jpg\\\">\",\n        \"target\": [\n          \"img[src$=\\\"Toolsqa-DZdwt2ul.jpg\\\"]\"\n        ],\n        \"failureSummary\": \"Fix any of the following:\\n  Element does not have an alt attribute\\n  aria-label attribute does not exist or is empty\\n  aria-labelledby attribute does not exist, references elements that do not exist or references elements that are empty\\n  Element has no title attribute\\n  Element's default semantics were not overridden with role=\\\"none\\\" or role=\\\"presentation\\\"\"\n      }\n    ]\n  },\n  {\n    \"id\": \"link-name\",\n    \"impact\": \"serious\",\n    \"tags\": [\n      \"cat.name-role-value\",\n      \"wcag2a\",\n      \"wcag244\",\n      \"wcag412\",\n      \"section508\",\n      \"section508.22.a\",\n      \"TTv5\",\n      \"TT6.a\",\n      \"EN-301-549\",\n      \"EN-9.2.4.4\",\n      \"EN-9.4.1.2\",\n      \"ACT\",\n      \"RGAAv4\",\n      \"RGAA-6.2.1\"\n    ],\n    \"description\": \"Ensure links have discernible text\",\n    \"help\": \"Links must have discernible text\",\n    \"helpUrl\": \"https://dequeuniversity.com/rules/axe/4.12/link-name?application=playwright\",\n    \"nodes\": [\n      {\n        \"any\": [\n          {\n            \"id\": \"has-visible-text\",\n            \"data\": null,\n            \"relatedNodes\": [],\n            \"impact\": \"serious\",\n            \"message\": \"Element does not have text that is visible to screen readers\"\n          },\n          {\n            \"id\": \"aria-label\",\n            \"data\": null,\n            \"relatedNodes\": [],\n            \"impact\": \"serious\",\n            \"message\": \"aria-label attribute does not exist or is empty\"\n          },\n          {\n            \"id\": \"aria-labelledby\",\n            \"data\": null,\n            \"relatedNodes\": [],\n            \"impact\": \"serious\",\n            \"message\": \"aria-labelledby attribute does not exist, references elements that do not exist or references elements that are empty\"\n          },\n          {\n            \"id\": \"non-empty-title\",\n            \"data\": {\n              \"messageKey\": \"noAttr\"\n            },\n            \"relatedNodes\": [],\n            \"impact\": \"serious\",\n            \"message\": \"Element has no title attribute\"\n          }\n        ],\n        \"all\": [],\n        \"none\": [\n          {\n            \"id\": \"focusable-no-name\",\n            \"data\": null,\n            \"relatedNodes\": [],\n            \"impact\": \"serious\",\n            \"message\": \"Element is in tab order and does not have accessible text\"\n          }\n        ],\n        \"impact\": \"serious\",\n        \"html\": \"<a href=\\\"https://demoqa.com\\\"><img src=\\\"/assets/Toolsqa-DZdwt2ul.jpg\\\"></a>\",\n        \"target\": [\n          \"a[href$=\\\"demoqa.com\\\"]\"\n        ],\n        \"failureSummary\": \"Fix all of the following:\\n  Element is in tab order and does not have accessible text\\n\\nFix any of the following:\\n  Element does not have text that is visible to screen readers\\n  aria-label attribute does not exist or is empty\\n  aria-labelledby attribute does not exist, references elements that do not exist or references elements that are empty\\n  Element has no title attribute\"\n      }\n    ]\n  }\n]\n"
                    }
                  ],
                  "stderr": [],
                  "retry": 0,
                  "startTime": "2026-06-25T11:11:15.105Z",
                  "annotations": [],
                  "attachments": [
                    {
                      "name": "screenshot",
                      "contentType": "image/png",
                      "path": "C:\\Arpita\\abPlaywrightE2Eautomation\\test-results\\accessibility-products-ful-f48cb-al-accessibility-violations\\test-failed-1.png"
                    },
                    {
                      "name": "video",
                      "contentType": "video/webm",
                      "path": "C:\\Arpita\\abPlaywrightE2Eautomation\\test-results\\accessibility-products-ful-f48cb-al-accessibility-violations\\video-1.webm"
                    },
                    {
                      "name": "video",
                      "contentType": "video/webm",
                      "path": "C:\\Arpita\\abPlaywrightE2Eautomation\\test-results\\accessibility-products-ful-f48cb-al-accessibility-violations\\video.webm"
                    },
                    {
                      "name": "error-context",
                      "contentType": "text/markdown",
                      "path": "C:\\Arpita\\abPlaywrightE2Eautomation\\test-results\\accessibility-products-ful-f48cb-al-accessibility-violations\\error-context.md"
                    },
                    {
                      "name": "trace",
                      "contentType": "application/zip",
                      "path": "C:\\Arpita\\abPlaywrightE2Eautomation\\test-results\\accessibility-products-ful-f48cb-al-accessibility-violations\\trace.zip"
                    }
                  ],
                  "errorLocation": {
                    "file": "C:\\Arpita\\abPlaywrightE2Eautomation\\tests\\accessibility\\products-full-a11y-scan.spec.ts",
                    "column": 5,
                    "line": 30
                  }
                },
                {
                  "workerIndex": 1,
                  "parallelIndex": 0,
                  "status": "failed",
                  "duration": 2452,
                  "error": {
                    "message": "Error: \u001b[2mexpect(\u001b[22m\u001b[31mreceived\u001b[39m\u001b[2m).\u001b[22mtoEqual\u001b[2m(\u001b[22m\u001b[32mexpected\u001b[39m\u001b[2m) // deep equality\u001b[22m\n\n\u001b[32m- Expected  -   1\u001b[39m\n\u001b[31m+ Received  + 162\u001b[39m\n\n\u001b[32m- Array []\u001b[39m\n\u001b[31m+ Array [\u001b[39m\n\u001b[31m+   Object {\u001b[39m\n\u001b[31m+     \"description\": \"Ensure <img> elements have alternative text or a role of none or presentation\",\u001b[39m\n\u001b[31m+     \"help\": \"Images must have alternative text\",\u001b[39m\n\u001b[31m+     \"helpUrl\": \"https://dequeuniversity.com/rules/axe/4.12/image-alt?application=playwright\",\u001b[39m\n\u001b[31m+     \"id\": \"image-alt\",\u001b[39m\n\u001b[31m+     \"impact\": \"critical\",\u001b[39m\n\u001b[31m+     \"nodes\": Array [\u001b[39m\n\u001b[31m+       Object {\u001b[39m\n\u001b[31m+         \"all\": Array [],\u001b[39m\n\u001b[31m+         \"any\": Array [\u001b[39m\n\u001b[31m+           Object {\u001b[39m\n\u001b[31m+             \"data\": null,\u001b[39m\n\u001b[31m+             \"id\": \"has-alt\",\u001b[39m\n\u001b[31m+             \"impact\": \"critical\",\u001b[39m\n\u001b[31m+             \"message\": \"Element does not have an alt attribute\",\u001b[39m\n\u001b[31m+             \"relatedNodes\": Array [],\u001b[39m\n\u001b[31m+           },\u001b[39m\n\u001b[31m+           Object {\u001b[39m\n\u001b[31m+             \"data\": null,\u001b[39m\n\u001b[31m+             \"id\": \"aria-label\",\u001b[39m\n\u001b[31m+             \"impact\": \"critical\",\u001b[39m\n\u001b[31m+             \"message\": \"aria-label attribute does not exist or is empty\",\u001b[39m\n\u001b[31m+             \"relatedNodes\": Array [],\u001b[39m\n\u001b[31m+           },\u001b[39m\n\u001b[31m+           Object {\u001b[39m\n\u001b[31m+             \"data\": null,\u001b[39m\n\u001b[31m+             \"id\": \"aria-labelledby\",\u001b[39m\n\u001b[31m+             \"impact\": \"critical\",\u001b[39m\n\u001b[31m+             \"message\": \"aria-labelledby attribute does not exist, references elements that do not exist or references elements that are empty\",\u001b[39m\n\u001b[31m+             \"relatedNodes\": Array [],\u001b[39m\n\u001b[31m+           },\u001b[39m\n\u001b[31m+           Object {\u001b[39m\n\u001b[31m+             \"data\": Object {\u001b[39m\n\u001b[31m+               \"messageKey\": \"noAttr\",\u001b[39m\n\u001b[31m+             },\u001b[39m\n\u001b[31m+             \"id\": \"non-empty-title\",\u001b[39m\n\u001b[31m+             \"impact\": \"critical\",\u001b[39m\n\u001b[31m+             \"message\": \"Element has no title attribute\",\u001b[39m\n\u001b[31m+             \"relatedNodes\": Array [],\u001b[39m\n\u001b[31m+           },\u001b[39m\n\u001b[31m+           Object {\u001b[39m\n\u001b[31m+             \"data\": null,\u001b[39m\n\u001b[31m+             \"id\": \"presentational-role\",\u001b[39m\n\u001b[31m+             \"impact\": \"critical\",\u001b[39m\n\u001b[31m+             \"message\": \"Element's default semantics were not overridden with role=\\\"none\\\" or role=\\\"presentation\\\"\",\u001b[39m\n\u001b[31m+             \"relatedNodes\": Array [],\u001b[39m\n\u001b[31m+           },\u001b[39m\n\u001b[31m+         ],\u001b[39m\n\u001b[31m+         \"failureSummary\": \"Fix any of the following:\u001b[39m\n\u001b[31m+   Element does not have an alt attribute\u001b[39m\n\u001b[31m+   aria-label attribute does not exist or is empty\u001b[39m\n\u001b[31m+   aria-labelledby attribute does not exist, references elements that do not exist or references elements that are empty\u001b[39m\n\u001b[31m+   Element has no title attribute\u001b[39m\n\u001b[31m+   Element's default semantics were not overridden with role=\\\"none\\\" or role=\\\"presentation\\\"\",\u001b[39m\n\u001b[31m+         \"html\": \"<img src=\\\"/assets/Toolsqa-DZdwt2ul.jpg\\\">\",\u001b[39m\n\u001b[31m+         \"impact\": \"critical\",\u001b[39m\n\u001b[31m+         \"none\": Array [],\u001b[39m\n\u001b[31m+         \"target\": Array [\u001b[39m\n\u001b[31m+           \"img[src$=\\\"Toolsqa-DZdwt2ul.jpg\\\"]\",\u001b[39m\n\u001b[31m+         ],\u001b[39m\n\u001b[31m+       },\u001b[39m\n\u001b[31m+     ],\u001b[39m\n\u001b[31m+     \"tags\": Array [\u001b[39m\n\u001b[31m+       \"cat.text-alternatives\",\u001b[39m\n\u001b[31m+       \"wcag2a\",\u001b[39m\n\u001b[31m+       \"wcag111\",\u001b[39m\n\u001b[31m+       \"section508\",\u001b[39m\n\u001b[31m+       \"section508.22.a\",\u001b[39m\n\u001b[31m+       \"TTv5\",\u001b[39m\n\u001b[31m+       \"TT7.a\",\u001b[39m\n\u001b[31m+       \"TT7.b\",\u001b[39m\n\u001b[31m+       \"EN-301-549\",\u001b[39m\n\u001b[31m+       \"EN-9.1.1.1\",\u001b[39m\n\u001b[31m+       \"ACT\",\u001b[39m\n\u001b[31m+       \"RGAAv4\",\u001b[39m\n\u001b[31m+       \"RGAA-1.1.1\",\u001b[39m\n\u001b[31m+     ],\u001b[39m\n\u001b[31m+   },\u001b[39m\n\u001b[31m+   Object {\u001b[39m\n\u001b[31m+     \"description\": \"Ensure links have discernible text\",\u001b[39m\n\u001b[31m+     \"help\": \"Links must have discernible text\",\u001b[39m\n\u001b[31m+     \"helpUrl\": \"https://dequeuniversity.com/rules/axe/4.12/link-name?application=playwright\",\u001b[39m\n\u001b[31m+     \"id\": \"link-name\",\u001b[39m\n\u001b[31m+     \"impact\": \"serious\",\u001b[39m\n\u001b[31m+     \"nodes\": Array [\u001b[39m\n\u001b[31m+       Object {\u001b[39m\n\u001b[31m+         \"all\": Array [],\u001b[39m\n\u001b[31m+         \"any\": Array [\u001b[39m\n\u001b[31m+           Object {\u001b[39m\n\u001b[31m+             \"data\": null,\u001b[39m\n\u001b[31m+             \"id\": \"has-visible-text\",\u001b[39m\n\u001b[31m+             \"impact\": \"serious\",\u001b[39m\n\u001b[31m+             \"message\": \"Element does not have text that is visible to screen readers\",\u001b[39m\n\u001b[31m+             \"relatedNodes\": Array [],\u001b[39m\n\u001b[31m+           },\u001b[39m\n\u001b[31m+           Object {\u001b[39m\n\u001b[31m+             \"data\": null,\u001b[39m\n\u001b[31m+             \"id\": \"aria-label\",\u001b[39m\n\u001b[31m+             \"impact\": \"serious\",\u001b[39m\n\u001b[31m+             \"message\": \"aria-label attribute does not exist or is empty\",\u001b[39m\n\u001b[31m+             \"relatedNodes\": Array [],\u001b[39m\n\u001b[31m+           },\u001b[39m\n\u001b[31m+           Object {\u001b[39m\n\u001b[31m+             \"data\": null,\u001b[39m\n\u001b[31m+             \"id\": \"aria-labelledby\",\u001b[39m\n\u001b[31m+             \"impact\": \"serious\",\u001b[39m\n\u001b[31m+             \"message\": \"aria-labelledby attribute does not exist, references elements that do not exist or references elements that are empty\",\u001b[39m\n\u001b[31m+             \"relatedNodes\": Array [],\u001b[39m\n\u001b[31m+           },\u001b[39m\n\u001b[31m+           Object {\u001b[39m\n\u001b[31m+             \"data\": Object {\u001b[39m\n\u001b[31m+               \"messageKey\": \"noAttr\",\u001b[39m\n\u001b[31m+             },\u001b[39m\n\u001b[31m+             \"id\": \"non-empty-title\",\u001b[39m\n\u001b[31m+             \"impact\": \"serious\",\u001b[39m\n\u001b[31m+             \"message\": \"Element has no title attribute\",\u001b[39m\n\u001b[31m+             \"relatedNodes\": Array [],\u001b[39m\n\u001b[31m+           },\u001b[39m\n\u001b[31m+         ],\u001b[39m\n\u001b[31m+         \"failureSummary\": \"Fix all of the following:\u001b[39m\n\u001b[31m+   Element is in tab order and does not have accessible text\u001b[39m\n\u001b[31m+\u001b[39m\n\u001b[31m+ Fix any of the following:\u001b[39m\n\u001b[31m+   Element does not have text that is visible to screen readers\u001b[39m\n\u001b[31m+   aria-label attribute does not exist or is empty\u001b[39m\n\u001b[31m+   aria-labelledby attribute does not exist, references elements that do not exist or references elements that are empty\u001b[39m\n\u001b[31m+   Element has no title attribute\",\u001b[39m\n\u001b[31m+         \"html\": \"<a href=\\\"https://demoqa.com\\\"><img src=\\\"/assets/Toolsqa-DZdwt2ul.jpg\\\"></a>\",\u001b[39m\n\u001b[31m+         \"impact\": \"serious\",\u001b[39m\n\u001b[31m+         \"none\": Array [\u001b[39m\n\u001b[31m+           Object {\u001b[39m\n\u001b[31m+             \"data\": null,\u001b[39m\n\u001b[31m+             \"id\": \"focusable-no-name\",\u001b[39m\n\u001b[31m+             \"impact\": \"serious\",\u001b[39m\n\u001b[31m+             \"message\": \"Element is in tab order and does not have accessible text\",\u001b[39m\n\u001b[31m+             \"relatedNodes\": Array [],\u001b[39m\n\u001b[31m+           },\u001b[39m\n\u001b[31m+         ],\u001b[39m\n\u001b[31m+         \"target\": Array [\u001b[39m\n\u001b[31m+           \"a[href$=\\\"demoqa.com\\\"]\",\u001b[39m\n\u001b[31m+         ],\u001b[39m\n\u001b[31m+       },\u001b[39m\n\u001b[31m+     ],\u001b[39m\n\u001b[31m+     \"tags\": Array [\u001b[39m\n\u001b[31m+       \"cat.name-role-value\",\u001b[39m\n\u001b[31m+       \"wcag2a\",\u001b[39m\n\u001b[31m+       \"wcag244\",\u001b[39m\n\u001b[31m+       \"wcag412\",\u001b[39m\n\u001b[31m+       \"section508\",\u001b[39m\n\u001b[31m+       \"section508.22.a\",\u001b[39m\n\u001b[31m+       \"TTv5\",\u001b[39m\n\u001b[31m+       \"TT6.a\",\u001b[39m\n\u001b[31m+       \"EN-301-549\",\u001b[39m\n\u001b[31m+       \"EN-9.2.4.4\",\u001b[39m\n\u001b[31m+       \"EN-9.4.1.2\",\u001b[39m\n\u001b[31m+       \"ACT\",\u001b[39m\n\u001b[31m+       \"RGAAv4\",\u001b[39m\n\u001b[31m+       \"RGAA-6.2.1\",\u001b[39m\n\u001b[31m+     ],\u001b[39m\n\u001b[31m+   },\u001b[39m\n\u001b[31m+ ]\u001b[39m",
                    "stack": "Error: \u001b[2mexpect(\u001b[22m\u001b[31mreceived\u001b[39m\u001b[2m).\u001b[22mtoEqual\u001b[2m(\u001b[22m\u001b[32mexpected\u001b[39m\u001b[2m) // deep equality\u001b[22m\n\n\u001b[32m- Expected  -   1\u001b[39m\n\u001b[31m+ Received  + 162\u001b[39m\n\n\u001b[32m- Array []\u001b[39m\n\u001b[31m+ Array [\u001b[39m\n\u001b[31m+   Object {\u001b[39m\n\u001b[31m+     \"description\": \"Ensure <img> elements have alternative text or a role of none or presentation\",\u001b[39m\n\u001b[31m+     \"help\": \"Images must have alternative text\",\u001b[39m\n\u001b[31m+     \"helpUrl\": \"https://dequeuniversity.com/rules/axe/4.12/image-alt?application=playwright\",\u001b[39m\n\u001b[31m+     \"id\": \"image-alt\",\u001b[39m\n\u001b[31m+     \"impact\": \"critical\",\u001b[39m\n\u001b[31m+     \"nodes\": Array [\u001b[39m\n\u001b[31m+       Object {\u001b[39m\n\u001b[31m+         \"all\": Array [],\u001b[39m\n\u001b[31m+         \"any\": Array [\u001b[39m\n\u001b[31m+           Object {\u001b[39m\n\u001b[31m+             \"data\": null,\u001b[39m\n\u001b[31m+             \"id\": \"has-alt\",\u001b[39m\n\u001b[31m+             \"impact\": \"critical\",\u001b[39m\n\u001b[31m+             \"message\": \"Element does not have an alt attribute\",\u001b[39m\n\u001b[31m+             \"relatedNodes\": Array [],\u001b[39m\n\u001b[31m+           },\u001b[39m\n\u001b[31m+           Object {\u001b[39m\n\u001b[31m+             \"data\": null,\u001b[39m\n\u001b[31m+             \"id\": \"aria-label\",\u001b[39m\n\u001b[31m+             \"impact\": \"critical\",\u001b[39m\n\u001b[31m+             \"message\": \"aria-label attribute does not exist or is empty\",\u001b[39m\n\u001b[31m+             \"relatedNodes\": Array [],\u001b[39m\n\u001b[31m+           },\u001b[39m\n\u001b[31m+           Object {\u001b[39m\n\u001b[31m+             \"data\": null,\u001b[39m\n\u001b[31m+             \"id\": \"aria-labelledby\",\u001b[39m\n\u001b[31m+             \"impact\": \"critical\",\u001b[39m\n\u001b[31m+             \"message\": \"aria-labelledby attribute does not exist, references elements that do not exist or references elements that are empty\",\u001b[39m\n\u001b[31m+             \"relatedNodes\": Array [],\u001b[39m\n\u001b[31m+           },\u001b[39m\n\u001b[31m+           Object {\u001b[39m\n\u001b[31m+             \"data\": Object {\u001b[39m\n\u001b[31m+               \"messageKey\": \"noAttr\",\u001b[39m\n\u001b[31m+             },\u001b[39m\n\u001b[31m+             \"id\": \"non-empty-title\",\u001b[39m\n\u001b[31m+             \"impact\": \"critical\",\u001b[39m\n\u001b[31m+             \"message\": \"Element has no title attribute\",\u001b[39m\n\u001b[31m+             \"relatedNodes\": Array [],\u001b[39m\n\u001b[31m+           },\u001b[39m\n\u001b[31m+           Object {\u001b[39m\n\u001b[31m+             \"data\": null,\u001b[39m\n\u001b[31m+             \"id\": \"presentational-role\",\u001b[39m\n\u001b[31m+             \"impact\": \"critical\",\u001b[39m\n\u001b[31m+             \"message\": \"Element's default semantics were not overridden with role=\\\"none\\\" or role=\\\"presentation\\\"\",\u001b[39m\n\u001b[31m+             \"relatedNodes\": Array [],\u001b[39m\n\u001b[31m+           },\u001b[39m\n\u001b[31m+         ],\u001b[39m\n\u001b[31m+         \"failureSummary\": \"Fix any of the following:\u001b[39m\n\u001b[31m+   Element does not have an alt attribute\u001b[39m\n\u001b[31m+   aria-label attribute does not exist or is empty\u001b[39m\n\u001b[31m+   aria-labelledby attribute does not exist, references elements that do not exist or references elements that are empty\u001b[39m\n\u001b[31m+   Element has no title attribute\u001b[39m\n\u001b[31m+   Element's default semantics were not overridden with role=\\\"none\\\" or role=\\\"presentation\\\"\",\u001b[39m\n\u001b[31m+         \"html\": \"<img src=\\\"/assets/Toolsqa-DZdwt2ul.jpg\\\">\",\u001b[39m\n\u001b[31m+         \"impact\": \"critical\",\u001b[39m\n\u001b[31m+         \"none\": Array [],\u001b[39m\n\u001b[31m+         \"target\": Array [\u001b[39m\n\u001b[31m+           \"img[src$=\\\"Toolsqa-DZdwt2ul.jpg\\\"]\",\u001b[39m\n\u001b[31m+         ],\u001b[39m\n\u001b[31m+       },\u001b[39m\n\u001b[31m+     ],\u001b[39m\n\u001b[31m+     \"tags\": Array [\u001b[39m\n\u001b[31m+       \"cat.text-alternatives\",\u001b[39m\n\u001b[31m+       \"wcag2a\",\u001b[39m\n\u001b[31m+       \"wcag111\",\u001b[39m\n\u001b[31m+       \"section508\",\u001b[39m\n\u001b[31m+       \"section508.22.a\",\u001b[39m\n\u001b[31m+       \"TTv5\",\u001b[39m\n\u001b[31m+       \"TT7.a\",\u001b[39m\n\u001b[31m+       \"TT7.b\",\u001b[39m\n\u001b[31m+       \"EN-301-549\",\u001b[39m\n\u001b[31m+       \"EN-9.1.1.1\",\u001b[39m\n\u001b[31m+       \"ACT\",\u001b[39m\n\u001b[31m+       \"RGAAv4\",\u001b[39m\n\u001b[31m+       \"RGAA-1.1.1\",\u001b[39m\n\u001b[31m+     ],\u001b[39m\n\u001b[31m+   },\u001b[39m\n\u001b[31m+   Object {\u001b[39m\n\u001b[31m+     \"description\": \"Ensure links have discernible text\",\u001b[39m\n\u001b[31m+     \"help\": \"Links must have discernible text\",\u001b[39m\n\u001b[31m+     \"helpUrl\": \"https://dequeuniversity.com/rules/axe/4.12/link-name?application=playwright\",\u001b[39m\n\u001b[31m+     \"id\": \"link-name\",\u001b[39m\n\u001b[31m+     \"impact\": \"serious\",\u001b[39m\n\u001b[31m+     \"nodes\": Array [\u001b[39m\n\u001b[31m+       Object {\u001b[39m\n\u001b[31m+         \"all\": Array [],\u001b[39m\n\u001b[31m+         \"any\": Array [\u001b[39m\n\u001b[31m+           Object {\u001b[39m\n\u001b[31m+             \"data\": null,\u001b[39m\n\u001b[31m+             \"id\": \"has-visible-text\",\u001b[39m\n\u001b[31m+             \"impact\": \"serious\",\u001b[39m\n\u001b[31m+             \"message\": \"Element does not have text that is visible to screen readers\",\u001b[39m\n\u001b[31m+             \"relatedNodes\": Array [],\u001b[39m\n\u001b[31m+           },\u001b[39m\n\u001b[31m+           Object {\u001b[39m\n\u001b[31m+             \"data\": null,\u001b[39m\n\u001b[31m+             \"id\": \"aria-label\",\u001b[39m\n\u001b[31m+             \"impact\": \"serious\",\u001b[39m\n\u001b[31m+             \"message\": \"aria-label attribute does not exist or is empty\",\u001b[39m\n\u001b[31m+             \"relatedNodes\": Array [],\u001b[39m\n\u001b[31m+           },\u001b[39m\n\u001b[31m+           Object {\u001b[39m\n\u001b[31m+             \"data\": null,\u001b[39m\n\u001b[31m+             \"id\": \"aria-labelledby\",\u001b[39m\n\u001b[31m+             \"impact\": \"serious\",\u001b[39m\n\u001b[31m+             \"message\": \"aria-labelledby attribute does not exist, references elements that do not exist or references elements that are empty\",\u001b[39m\n\u001b[31m+             \"relatedNodes\": Array [],\u001b[39m\n\u001b[31m+           },\u001b[39m\n\u001b[31m+           Object {\u001b[39m\n\u001b[31m+             \"data\": Object {\u001b[39m\n\u001b[31m+               \"messageKey\": \"noAttr\",\u001b[39m\n\u001b[31m+             },\u001b[39m\n\u001b[31m+             \"id\": \"non-empty-title\",\u001b[39m\n\u001b[31m+             \"impact\": \"serious\",\u001b[39m\n\u001b[31m+             \"message\": \"Element has no title attribute\",\u001b[39m\n\u001b[31m+             \"relatedNodes\": Array [],\u001b[39m\n\u001b[31m+           },\u001b[39m\n\u001b[31m+         ],\u001b[39m\n\u001b[31m+         \"failureSummary\": \"Fix all of the following:\u001b[39m\n\u001b[31m+   Element is in tab order and does not have accessible text\u001b[39m\n\u001b[31m+\u001b[39m\n\u001b[31m+ Fix any of the following:\u001b[39m\n\u001b[31m+   Element does not have text that is visible to screen readers\u001b[39m\n\u001b[31m+   aria-label attribute does not exist or is empty\u001b[39m\n\u001b[31m+   aria-labelledby attribute does not exist, references elements that do not exist or references elements that are empty\u001b[39m\n\u001b[31m+   Element has no title attribute\",\u001b[39m\n\u001b[31m+         \"html\": \"<a href=\\\"https://demoqa.com\\\"><img src=\\\"/assets/Toolsqa-DZdwt2ul.jpg\\\"></a>\",\u001b[39m\n\u001b[31m+         \"impact\": \"serious\",\u001b[39m\n\u001b[31m+         \"none\": Array [\u001b[39m\n\u001b[31m+           Object {\u001b[39m\n\u001b[31m+             \"data\": null,\u001b[39m\n\u001b[31m+             \"id\": \"focusable-no-name\",\u001b[39m\n\u001b[31m+             \"impact\": \"serious\",\u001b[39m\n\u001b[31m+             \"message\": \"Element is in tab order and does not have accessible text\",\u001b[39m\n\u001b[31m+             \"relatedNodes\": Array [],\u001b[39m\n\u001b[31m+           },\u001b[39m\n\u001b[31m+         ],\u001b[39m\n\u001b[31m+         \"target\": Array [\u001b[39m\n\u001b[31m+           \"a[href$=\\\"demoqa.com\\\"]\",\u001b[39m\n\u001b[31m+         ],\u001b[39m\n\u001b[31m+       },\u001b[39m\n\u001b[31m+     ],\u001b[39m\n\u001b[31m+     \"tags\": Array [\u001b[39m\n\u001b[31m+       \"cat.name-role-value\",\u001b[39m\n\u001b[31m+       \"wcag2a\",\u001b[39m\n\u001b[31m+       \"wcag244\",\u001b[39m\n\u001b[31m+       \"wcag412\",\u001b[39m\n\u001b[31m+       \"section508\",\u001b[39m\n\u001b[31m+       \"section508.22.a\",\u001b[39m\n\u001b[31m+       \"TTv5\",\u001b[39m\n\u001b[31m+       \"TT6.a\",\u001b[39m\n\u001b[31m+       \"EN-301-549\",\u001b[39m\n\u001b[31m+       \"EN-9.2.4.4\",\u001b[39m\n\u001b[31m+       \"EN-9.4.1.2\",\u001b[39m\n\u001b[31m+       \"ACT\",\u001b[39m\n\u001b[31m+       \"RGAAv4\",\u001b[39m\n\u001b[31m+       \"RGAA-6.2.1\",\u001b[39m\n\u001b[31m+     ],\u001b[39m\n\u001b[31m+   },\u001b[39m\n\u001b[31m+ ]\u001b[39m\n    at C:\\Arpita\\abPlaywrightE2Eautomation\\tests\\accessibility\\products-full-a11y-scan.spec.ts:30:5",
                    "location": {
                      "file": "C:\\Arpita\\abPlaywrightE2Eautomation\\tests\\accessibility\\products-full-a11y-scan.spec.ts",
                      "column": 5,
                      "line": 30
                    },
                    "snippet": "\u001b[0m \u001b[90m 28 |\u001b[39m   expect(\n \u001b[90m 29 |\u001b[39m     accessibilityScanResults\u001b[33m.\u001b[39mviolations\n\u001b[31m\u001b[1m>\u001b[22m\u001b[39m\u001b[90m 30 |\u001b[39m   )\u001b[33m.\u001b[39mtoEqual([])\u001b[33m;\u001b[39m\n \u001b[90m    |\u001b[39m     \u001b[31m\u001b[1m^\u001b[22m\u001b[39m\n \u001b[90m 31 |\u001b[39m })\u001b[33m;\u001b[39m\u001b[0m"
                  },
                  "errors": [
                    {
                      "location": {
                        "file": "C:\\Arpita\\abPlaywrightE2Eautomation\\tests\\accessibility\\products-full-a11y-scan.spec.ts",
                        "column": 5,
                        "line": 30
                      },
                      "message": "Error: \u001b[2mexpect(\u001b[22m\u001b[31mreceived\u001b[39m\u001b[2m).\u001b[22mtoEqual\u001b[2m(\u001b[22m\u001b[32mexpected\u001b[39m\u001b[2m) // deep equality\u001b[22m\n\n\u001b[32m- Expected  -   1\u001b[39m\n\u001b[31m+ Received  + 162\u001b[39m\n\n\u001b[32m- Array []\u001b[39m\n\u001b[31m+ Array [\u001b[39m\n\u001b[31m+   Object {\u001b[39m\n\u001b[31m+     \"description\": \"Ensure <img> elements have alternative text or a role of none or presentation\",\u001b[39m\n\u001b[31m+     \"help\": \"Images must have alternative text\",\u001b[39m\n\u001b[31m+     \"helpUrl\": \"https://dequeuniversity.com/rules/axe/4.12/image-alt?application=playwright\",\u001b[39m\n\u001b[31m+     \"id\": \"image-alt\",\u001b[39m\n\u001b[31m+     \"impact\": \"critical\",\u001b[39m\n\u001b[31m+     \"nodes\": Array [\u001b[39m\n\u001b[31m+       Object {\u001b[39m\n\u001b[31m+         \"all\": Array [],\u001b[39m\n\u001b[31m+         \"any\": Array [\u001b[39m\n\u001b[31m+           Object {\u001b[39m\n\u001b[31m+             \"data\": null,\u001b[39m\n\u001b[31m+             \"id\": \"has-alt\",\u001b[39m\n\u001b[31m+             \"impact\": \"critical\",\u001b[39m\n\u001b[31m+             \"message\": \"Element does not have an alt attribute\",\u001b[39m\n\u001b[31m+             \"relatedNodes\": Array [],\u001b[39m\n\u001b[31m+           },\u001b[39m\n\u001b[31m+           Object {\u001b[39m\n\u001b[31m+             \"data\": null,\u001b[39m\n\u001b[31m+             \"id\": \"aria-label\",\u001b[39m\n\u001b[31m+             \"impact\": \"critical\",\u001b[39m\n\u001b[31m+             \"message\": \"aria-label attribute does not exist or is empty\",\u001b[39m\n\u001b[31m+             \"relatedNodes\": Array [],\u001b[39m\n\u001b[31m+           },\u001b[39m\n\u001b[31m+           Object {\u001b[39m\n\u001b[31m+             \"data\": null,\u001b[39m\n\u001b[31m+             \"id\": \"aria-labelledby\",\u001b[39m\n\u001b[31m+             \"impact\": \"critical\",\u001b[39m\n\u001b[31m+             \"message\": \"aria-labelledby attribute does not exist, references elements that do not exist or references elements that are empty\",\u001b[39m\n\u001b[31m+             \"relatedNodes\": Array [],\u001b[39m\n\u001b[31m+           },\u001b[39m\n\u001b[31m+           Object {\u001b[39m\n\u001b[31m+             \"data\": Object {\u001b[39m\n\u001b[31m+               \"messageKey\": \"noAttr\",\u001b[39m\n\u001b[31m+             },\u001b[39m\n\u001b[31m+             \"id\": \"non-empty-title\",\u001b[39m\n\u001b[31m+             \"impact\": \"critical\",\u001b[39m\n\u001b[31m+             \"message\": \"Element has no title attribute\",\u001b[39m\n\u001b[31m+             \"relatedNodes\": Array [],\u001b[39m\n\u001b[31m+           },\u001b[39m\n\u001b[31m+           Object {\u001b[39m\n\u001b[31m+             \"data\": null,\u001b[39m\n\u001b[31m+             \"id\": \"presentational-role\",\u001b[39m\n\u001b[31m+             \"impact\": \"critical\",\u001b[39m\n\u001b[31m+             \"message\": \"Element's default semantics were not overridden with role=\\\"none\\\" or role=\\\"presentation\\\"\",\u001b[39m\n\u001b[31m+             \"relatedNodes\": Array [],\u001b[39m\n\u001b[31m+           },\u001b[39m\n\u001b[31m+         ],\u001b[39m\n\u001b[31m+         \"failureSummary\": \"Fix any of the following:\u001b[39m\n\u001b[31m+   Element does not have an alt attribute\u001b[39m\n\u001b[31m+   aria-label attribute does not exist or is empty\u001b[39m\n\u001b[31m+   aria-labelledby attribute does not exist, references elements that do not exist or references elements that are empty\u001b[39m\n\u001b[31m+   Element has no title attribute\u001b[39m\n\u001b[31m+   Element's default semantics were not overridden with role=\\\"none\\\" or role=\\\"presentation\\\"\",\u001b[39m\n\u001b[31m+         \"html\": \"<img src=\\\"/assets/Toolsqa-DZdwt2ul.jpg\\\">\",\u001b[39m\n\u001b[31m+         \"impact\": \"critical\",\u001b[39m\n\u001b[31m+         \"none\": Array [],\u001b[39m\n\u001b[31m+         \"target\": Array [\u001b[39m\n\u001b[31m+           \"img[src$=\\\"Toolsqa-DZdwt2ul.jpg\\\"]\",\u001b[39m\n\u001b[31m+         ],\u001b[39m\n\u001b[31m+       },\u001b[39m\n\u001b[31m+     ],\u001b[39m\n\u001b[31m+     \"tags\": Array [\u001b[39m\n\u001b[31m+       \"cat.text-alternatives\",\u001b[39m\n\u001b[31m+       \"wcag2a\",\u001b[39m\n\u001b[31m+       \"wcag111\",\u001b[39m\n\u001b[31m+       \"section508\",\u001b[39m\n\u001b[31m+       \"section508.22.a\",\u001b[39m\n\u001b[31m+       \"TTv5\",\u001b[39m\n\u001b[31m+       \"TT7.a\",\u001b[39m\n\u001b[31m+       \"TT7.b\",\u001b[39m\n\u001b[31m+       \"EN-301-549\",\u001b[39m\n\u001b[31m+       \"EN-9.1.1.1\",\u001b[39m\n\u001b[31m+       \"ACT\",\u001b[39m\n\u001b[31m+       \"RGAAv4\",\u001b[39m\n\u001b[31m+       \"RGAA-1.1.1\",\u001b[39m\n\u001b[31m+     ],\u001b[39m\n\u001b[31m+   },\u001b[39m\n\u001b[31m+   Object {\u001b[39m\n\u001b[31m+     \"description\": \"Ensure links have discernible text\",\u001b[39m\n\u001b[31m+     \"help\": \"Links must have discernible text\",\u001b[39m\n\u001b[31m+     \"helpUrl\": \"https://dequeuniversity.com/rules/axe/4.12/link-name?application=playwright\",\u001b[39m\n\u001b[31m+     \"id\": \"link-name\",\u001b[39m\n\u001b[31m+     \"impact\": \"serious\",\u001b[39m\n\u001b[31m+     \"nodes\": Array [\u001b[39m\n\u001b[31m+       Object {\u001b[39m\n\u001b[31m+         \"all\": Array [],\u001b[39m\n\u001b[31m+         \"any\": Array [\u001b[39m\n\u001b[31m+           Object {\u001b[39m\n\u001b[31m+             \"data\": null,\u001b[39m\n\u001b[31m+             \"id\": \"has-visible-text\",\u001b[39m\n\u001b[31m+             \"impact\": \"serious\",\u001b[39m\n\u001b[31m+             \"message\": \"Element does not have text that is visible to screen readers\",\u001b[39m\n\u001b[31m+             \"relatedNodes\": Array [],\u001b[39m\n\u001b[31m+           },\u001b[39m\n\u001b[31m+           Object {\u001b[39m\n\u001b[31m+             \"data\": null,\u001b[39m\n\u001b[31m+             \"id\": \"aria-label\",\u001b[39m\n\u001b[31m+             \"impact\": \"serious\",\u001b[39m\n\u001b[31m+             \"message\": \"aria-label attribute does not exist or is empty\",\u001b[39m\n\u001b[31m+             \"relatedNodes\": Array [],\u001b[39m\n\u001b[31m+           },\u001b[39m\n\u001b[31m+           Object {\u001b[39m\n\u001b[31m+             \"data\": null,\u001b[39m\n\u001b[31m+             \"id\": \"aria-labelledby\",\u001b[39m\n\u001b[31m+             \"impact\": \"serious\",\u001b[39m\n\u001b[31m+             \"message\": \"aria-labelledby attribute does not exist, references elements that do not exist or references elements that are empty\",\u001b[39m\n\u001b[31m+             \"relatedNodes\": Array [],\u001b[39m\n\u001b[31m+           },\u001b[39m\n\u001b[31m+           Object {\u001b[39m\n\u001b[31m+             \"data\": Object {\u001b[39m\n\u001b[31m+               \"messageKey\": \"noAttr\",\u001b[39m\n\u001b[31m+             },\u001b[39m\n\u001b[31m+             \"id\": \"non-empty-title\",\u001b[39m\n\u001b[31m+             \"impact\": \"serious\",\u001b[39m\n\u001b[31m+             \"message\": \"Element has no title attribute\",\u001b[39m\n\u001b[31m+             \"relatedNodes\": Array [],\u001b[39m\n\u001b[31m+           },\u001b[39m\n\u001b[31m+         ],\u001b[39m\n\u001b[31m+         \"failureSummary\": \"Fix all of the following:\u001b[39m\n\u001b[31m+   Element is in tab order and does not have accessible text\u001b[39m\n\u001b[31m+\u001b[39m\n\u001b[31m+ Fix any of the following:\u001b[39m\n\u001b[31m+   Element does not have text that is visible to screen readers\u001b[39m\n\u001b[31m+   aria-label attribute does not exist or is empty\u001b[39m\n\u001b[31m+   aria-labelledby attribute does not exist, references elements that do not exist or references elements that are empty\u001b[39m\n\u001b[31m+   Element has no title attribute\",\u001b[39m\n\u001b[31m+         \"html\": \"<a href=\\\"https://demoqa.com\\\"><img src=\\\"/assets/Toolsqa-DZdwt2ul.jpg\\\"></a>\",\u001b[39m\n\u001b[31m+         \"impact\": \"serious\",\u001b[39m\n\u001b[31m+         \"none\": Array [\u001b[39m\n\u001b[31m+           Object {\u001b[39m\n\u001b[31m+             \"data\": null,\u001b[39m\n\u001b[31m+             \"id\": \"focusable-no-name\",\u001b[39m\n\u001b[31m+             \"impact\": \"serious\",\u001b[39m\n\u001b[31m+             \"message\": \"Element is in tab order and does not have accessible text\",\u001b[39m\n\u001b[31m+             \"relatedNodes\": Array [],\u001b[39m\n\u001b[31m+           },\u001b[39m\n\u001b[31m+         ],\u001b[39m\n\u001b[31m+         \"target\": Array [\u001b[39m\n\u001b[31m+           \"a[href$=\\\"demoqa.com\\\"]\",\u001b[39m\n\u001b[31m+         ],\u001b[39m\n\u001b[31m+       },\u001b[39m\n\u001b[31m+     ],\u001b[39m\n\u001b[31m+     \"tags\": Array [\u001b[39m\n\u001b[31m+       \"cat.name-role-value\",\u001b[39m\n\u001b[31m+       \"wcag2a\",\u001b[39m\n\u001b[31m+       \"wcag244\",\u001b[39m\n\u001b[31m+       \"wcag412\",\u001b[39m\n\u001b[31m+       \"section508\",\u001b[39m\n\u001b[31m+       \"section508.22.a\",\u001b[39m\n\u001b[31m+       \"TTv5\",\u001b[39m\n\u001b[31m+       \"TT6.a\",\u001b[39m\n\u001b[31m+       \"EN-301-549\",\u001b[39m\n\u001b[31m+       \"EN-9.2.4.4\",\u001b[39m\n\u001b[31m+       \"EN-9.4.1.2\",\u001b[39m\n\u001b[31m+       \"ACT\",\u001b[39m\n\u001b[31m+       \"RGAAv4\",\u001b[39m\n\u001b[31m+       \"RGAA-6.2.1\",\u001b[39m\n\u001b[31m+     ],\u001b[39m\n\u001b[31m+   },\u001b[39m\n\u001b[31m+ ]\u001b[39m\n\n\u001b[0m \u001b[90m 28 |\u001b[39m   expect(\n \u001b[90m 29 |\u001b[39m     accessibilityScanResults\u001b[33m.\u001b[39mviolations\n\u001b[31m\u001b[1m>\u001b[22m\u001b[39m\u001b[90m 30 |\u001b[39m   )\u001b[33m.\u001b[39mtoEqual([])\u001b[33m;\u001b[39m\n \u001b[90m    |\u001b[39m     \u001b[31m\u001b[1m^\u001b[22m\u001b[39m\n \u001b[90m 31 |\u001b[39m })\u001b[33m;\u001b[39m\u001b[0m\n\u001b[2m    at C:\\Arpita\\abPlaywrightE2Eautomation\\tests\\accessibility\\products-full-a11y-scan.spec.ts:30:5\u001b[22m"
                    }
                  ],
                  "stdout": [
                    {
                      "text": "[\n  {\n    \"id\": \"image-alt\",\n    \"impact\": \"critical\",\n    \"tags\": [\n      \"cat.text-alternatives\",\n      \"wcag2a\",\n      \"wcag111\",\n      \"section508\",\n      \"section508.22.a\",\n      \"TTv5\",\n      \"TT7.a\",\n      \"TT7.b\",\n      \"EN-301-549\",\n      \"EN-9.1.1.1\",\n      \"ACT\",\n      \"RGAAv4\",\n      \"RGAA-1.1.1\"\n    ],\n    \"description\": \"Ensure <img> elements have alternative text or a role of none or presentation\",\n    \"help\": \"Images must have alternative text\",\n    \"helpUrl\": \"https://dequeuniversity.com/rules/axe/4.12/image-alt?application=playwright\",\n    \"nodes\": [\n      {\n        \"any\": [\n          {\n            \"id\": \"has-alt\",\n            \"data\": null,\n            \"relatedNodes\": [],\n            \"impact\": \"critical\",\n            \"message\": \"Element does not have an alt attribute\"\n          },\n          {\n            \"id\": \"aria-label\",\n            \"data\": null,\n            \"relatedNodes\": [],\n            \"impact\": \"critical\",\n            \"message\": \"aria-label attribute does not exist or is empty\"\n          },\n          {\n            \"id\": \"aria-labelledby\",\n            \"data\": null,\n            \"relatedNodes\": [],\n            \"impact\": \"critical\",\n            \"message\": \"aria-labelledby attribute does not exist, references elements that do not exist or references elements that are empty\"\n          },\n          {\n            \"id\": \"non-empty-title\",\n            \"data\": {\n              \"messageKey\": \"noAttr\"\n            },\n            \"relatedNodes\": [],\n            \"impact\": \"critical\",\n            \"message\": \"Element has no title attribute\"\n          },\n          {\n            \"id\": \"presentational-role\",\n            \"data\": null,\n            \"relatedNodes\": [],\n            \"impact\": \"critical\",\n            \"message\": \"Element's default semantics were not overridden with role=\\\"none\\\" or role=\\\"presentation\\\"\"\n          }\n        ],\n        \"all\": [],\n        \"none\": [],\n        \"impact\": \"critical\",\n        \"html\": \"<img src=\\\"/assets/Toolsqa-DZdwt2ul.jpg\\\">\",\n        \"target\": [\n          \"img[src$=\\\"Toolsqa-DZdwt2ul.jpg\\\"]\"\n        ],\n        \"failureSummary\": \"Fix any of the following:\\n  Element does not have an alt attribute\\n  aria-label attribute does not exist or is empty\\n  aria-labelledby attribute does not exist, references elements that do not exist or references elements that are empty\\n  Element has no title attribute\\n  Element's default semantics were not overridden with role=\\\"none\\\" or role=\\\"presentation\\\"\"\n      }\n    ]\n  },\n  {\n    \"id\": \"link-name\",\n    \"impact\": \"serious\",\n    \"tags\": [\n      \"cat.name-role-value\",\n      \"wcag2a\",\n      \"wcag244\",\n      \"wcag412\",\n      \"section508\",\n      \"section508.22.a\",\n      \"TTv5\",\n      \"TT6.a\",\n      \"EN-301-549\",\n      \"EN-9.2.4.4\",\n      \"EN-9.4.1.2\",\n      \"ACT\",\n      \"RGAAv4\",\n      \"RGAA-6.2.1\"\n    ],\n    \"description\": \"Ensure links have discernible text\",\n    \"help\": \"Links must have discernible text\",\n    \"helpUrl\": \"https://dequeuniversity.com/rules/axe/4.12/link-name?application=playwright\",\n    \"nodes\": [\n      {\n        \"any\": [\n          {\n            \"id\": \"has-visible-text\",\n            \"data\": null,\n            \"relatedNodes\": [],\n            \"impact\": \"serious\",\n            \"message\": \"Element does not have text that is visible to screen readers\"\n          },\n          {\n            \"id\": \"aria-label\",\n            \"data\": null,\n            \"relatedNodes\": [],\n            \"impact\": \"serious\",\n            \"message\": \"aria-label attribute does not exist or is empty\"\n          },\n          {\n            \"id\": \"aria-labelledby\",\n            \"data\": null,\n            \"relatedNodes\": [],\n            \"impact\": \"serious\",\n            \"message\": \"aria-labelledby attribute does not exist, references elements that do not exist or references elements that are empty\"\n          },\n          {\n            \"id\": \"non-empty-title\",\n            \"data\": {\n              \"messageKey\": \"noAttr\"\n            },\n            \"relatedNodes\": [],\n            \"impact\": \"serious\",\n            \"message\": \"Element has no title attribute\"\n          }\n        ],\n        \"all\": [],\n        \"none\": [\n          {\n            \"id\": \"focusable-no-name\",\n            \"data\": null,\n            \"relatedNodes\": [],\n            \"impact\": \"serious\",\n            \"message\": \"Element is in tab order and does not have accessible text\"\n          }\n        ],\n        \"impact\": \"serious\",\n        \"html\": \"<a href=\\\"https://demoqa.com\\\"><img src=\\\"/assets/Toolsqa-DZdwt2ul.jpg\\\"></a>\",\n        \"target\": [\n          \"a[href$=\\\"demoqa.com\\\"]\"\n        ],\n        \"failureSummary\": \"Fix all of the following:\\n  Element is in tab order and does not have accessible text\\n\\nFix any of the following:\\n  Element does not have text that is visible to screen readers\\n  aria-label attribute does not exist or is empty\\n  aria-labelledby attribute does not exist, references elements that do not exist or references elements that are empty\\n  Element has no title attribute\"\n      }\n    ]\n  }\n]\n"
                    }
                  ],
                  "stderr": [],
                  "retry": 1,
                  "startTime": "2026-06-25T11:11:19.203Z",
                  "annotations": [],
                  "attachments": [
                    {
                      "name": "screenshot",
                      "contentType": "image/png",
                      "path": "C:\\Arpita\\abPlaywrightE2Eautomation\\test-results\\accessibility-products-ful-f48cb-al-accessibility-violations-retry1\\test-failed-1.png"
                    },
                    {
                      "name": "video",
                      "contentType": "video/webm",
                      "path": "C:\\Arpita\\abPlaywrightE2Eautomation\\test-results\\accessibility-products-ful-f48cb-al-accessibility-violations-retry1\\video.webm"
                    },
                    {
                      "name": "video",
                      "contentType": "video/webm",
                      "path": "C:\\Arpita\\abPlaywrightE2Eautomation\\test-results\\accessibility-products-ful-f48cb-al-accessibility-violations-retry1\\video-1.webm"
                    },
                    {
                      "name": "error-context",
                      "contentType": "text/markdown",
                      "path": "C:\\Arpita\\abPlaywrightE2Eautomation\\test-results\\accessibility-products-ful-f48cb-al-accessibility-violations-retry1\\error-context.md"
                    },
                    {
                      "name": "trace",
                      "contentType": "application/zip",
                      "path": "C:\\Arpita\\abPlaywrightE2Eautomation\\test-results\\accessibility-products-ful-f48cb-al-accessibility-violations-retry1\\trace.zip"
                    }
                  ],
                  "errorLocation": {
                    "file": "C:\\Arpita\\abPlaywrightE2Eautomation\\tests\\accessibility\\products-full-a11y-scan.spec.ts",
                    "column": 5,
                    "line": 30
                  }
                }
              ],
              "status": "unexpected"
            }
          ],
          "id": "9239004a760b63c03b34-64b6072a201915a77f7d",
          "file": "accessibility/products-full-a11y-scan.spec.ts",
          "line": 6,
          "column": 1
        }
      ]
    }
  ],
  "errors": [],
  "stats": {
    "startTime": "2026-06-25T11:11:14.057Z",
    "duration": 8396.583,
    "expected": 0,
    "skipped": 0,
    "unexpected": 1,
    "flaky": 0
  }
}